Metadata-Version: 2.1
Name: datainfo
Version: 0.1.3
Summary: List general information of datasets within a data file commonly used in Atmospheric Science.
Home-page: https://github.com/hong-chen/datainfo
Author: Hong Chen, Yixing Shao
Author-email: me@hongchen.cz, yixingshao@foxmail.com
License: MIT
Keywords: data info list variable utilities
Platform: UNKNOWN
Classifier: Development Status :: 3 - Alpha
Classifier: License :: OSI Approved :: MIT License
Classifier: Programming Language :: Python :: 3.6
Classifier: Topic :: Scientific/Engineering :: Atmospheric Science
Requires-Python: ~=3.6
